broad_babel/__init__.py
broad_babel/data.py
broad_babel/query.py
broad_babel-0.1.28.dist-info/METADATA
broad_babel-0.1.28.dist-info/WHEEL
broad_babel-0.1.28.dist-info/licenses/LICENSE
broad_babel-0.1.28.dist-info/RECORD
