Metadata-Version: 2.4
Name: broad-babel
Version: 0.1.28
Summary: A translator of Broad and JUMP ids to more conventional names.
Project-URL: Homepage, https://github.com/broadinstitute/monorepo/tree/main/libs/jump_babel
Author: Alan Munoz
License-File: LICENSE
Requires-Python: <3.12,>=3.10
Requires-Dist: adbc-driver-sqlite<0.9,>=0.8.0
Requires-Dist: polars<2,>=1.5.0
Requires-Dist: pooch<2,>=1.7.0
Requires-Dist: pyarrow>=16.1.0
